{
  "id": "eb7b3a55-bb6f-4944-8323-68aff319cdf6",
  "slug": "understanding-the-60-day-notice-a-deep-dive-into-the-warn-act",
  "title": "Understanding the 60-Day Notice: A Deep Dive into the WARN Act",
  "description": "Explore the intricacies of the 60-day notice requirement under the WARN Act, its implications for companies, and opportunities for distressed asset buyers.",
  "excerpt": "In today's fast-paced corporate world, the specter of layoffs looms large, often serving as a distress signal for impending financial challenges within an organization. For professionals in...",
  "body": "In today's fast-paced corporate world, the specter of layoffs looms large, often serving as a distress signal for impending financial challenges within an organization. For professionals in distressed asset acquisition, understanding the nuances of the Worker Adjustment and Retraining Notification (WARN) Act's 60-day notice requirement is crucial. This legislation not only impacts employers and employees but also creates potential opportunities for those prepared to navigate the complexities of corporate distress.\n\n## Quick Answer\n- **The WARN Act's 60-day notice requirement is designed to provide workers with advance warning of mass layoffs or plant closures.** This federal law applies to employers with 100 or more employees, mandating that they provide written notice to affected workers, state dislocated worker units, and local governments.\n- **Failure to comply with the WARN Act can result in significant penalties for employers, including back pay for each day of violation and a $500 fine for each day of non-compliance.** These penalties underscore the importance of adhering to the notice period to avoid additional financial burdens.\n- **The 60-day notice can trigger a ripple effect in the market, providing early signals of corporate distress.** For asset buyers, this period offers a window to assess potential acquisition targets and prepare for opportunities arising from the company's financial challenges.\n- **Exceptions to the 60-day notice rule exist, such as unforeseeable business circumstances, natural disasters, and faltering company exceptions.** These exceptions can complicate the landscape, requiring careful due diligence from investors and asset buyers.\n- **Understanding state-specific WARN Act regulations is essential, as many states have implemented their own versions of the law with varying thresholds and requirements.** This adds another layer of complexity for companies operating in multiple jurisdictions.\n\n## Market Snapshot\nThe current landscape of corporate layoffs and plant closures paints a stark picture of economic volatility. According to recent data from the Bureau of Labor Statistics, over 1.4 million workers were affected by mass layoffs in 2025, marking a significant increase from previous years. This uptick reflects broader economic challenges, including supply chain disruptions, inflationary pressures, and shifting consumer demands. ![black and white building during daytime](https://images.unsplash.com/photo-1588253197754-420d2d818035?crop=entropy&cs=tinysrgb&fit=max&fm=jpg&ixid=M3w4ODA0MDZ8MHwxfHNlYXJjaHwxfHxsYXlvZmZzJTIwY29ycG9yYXRlfGVufDF8MHx8fDE3NzE3ODAxMzl8MA&ixlib=rb-4.1.0&q=80&w=1080&w=1200&q=80)\n*Photo: Photo by [Abhishek Anand](https://unsplash.com/@anand__a) on [Unsplash](https://unsplash.com)*\n\nIn 2025, several high-profile companies, such as General Electric and Ford, announced significant layoffs, citing restructuring efforts and declining sales. General Electric, for instance, laid off approximately 10,000 employees as part of its global restructuring strategy aimed at streamlining operations and cutting costs. Similarly, Ford's decision to close multiple manufacturing plants resulted in the loss of over 8,000 jobs, highlighting the impact of technological advancements and the shift towards electric vehicles.\n\nThe rise in layoffs has intensified scrutiny on the application of the WARN Act, particularly in sectors like manufacturing, retail, and technology. As companies grapple with economic uncertainties, compliance with the 60-day notice requirement becomes a critical aspect of operational strategy. For distressed asset buyers, these circumstances present unique opportunities to acquire assets at a reduced cost and capitalize on the potential for future growth.\n\nThe technology sector, in particular, has experienced a wave of layoffs due to rapid advancements and competitive pressures. In 2025, tech giants like Meta and Twitter announced layoffs affecting thousands of employees, as they sought to realign their business models and focus on core competencies. These developments underscore the importance of staying informed about industry trends and monitoring the regulatory landscape to identify potential acquisition targets.\n\n## Step-by-Step Guide\n1. **Identify Potential Targets:** Begin by monitoring news outlets, industry reports, and financial disclosures for signs of corporate distress. Companies announcing layoffs, restructuring, or declining earnings may signal potential acquisition opportunities.\n\n2. **Conduct Due Diligence:** Once a target is identified, perform a thorough analysis of the company's financial health, including balance sheets, cash flow statements, and debt levels. Understanding the underlying reasons for layoffs or plant closures is crucial to assessing the viability of an acquisition.\n\n3. **Evaluate Asset Value:** Assess the value of the company's assets, including real estate, equipment, and intellectual property. This step involves working with appraisers and industry experts to determine fair market value and identify any potential liabilities.\n\n4. **Navigate Legal and Regulatory Requirements:** Ensure compliance with the WARN Act and any state-specific regulations. Consult with legal counsel to understand the implications of the 60-day notice requirement and any exceptions that may apply.\n\n5. **Negotiate and Execute the Deal:** Engage with the company's management and stakeholders to negotiate terms and finalize the transaction. This process requires a strategic approach to valuation, financing, and risk management. ![a kite is flying high in the sky](https://images.unsplash.com/photo-1633690803733-dbd3e4cbb405?crop=entropy&cs=tinysrgb&fit=max&fm=jpg&ixid=M3w4ODA0MDZ8MHwxfHNlYXJjaHwyfHx0aGUlMjBkYXklMjBub3RpY2UlMjBkZWVwfGVufDF8MHx8fDE3NzE3ODAxMzh8MA&ixlib=rb-4.1.0&q=80&w=1080&w=1200&q=80)\n*Photo: Photo by [Marcos Romero](https://unsplash.com/@marcos265) on [Unsplash](https://unsplash.com)*\n\n## Decision Framework\nIf a company is facing declining revenues and announces layoffs, then it may be a prime target for asset acquisition. In such scenarios, conducting thorough due diligence and understanding the company's financial position is essential to making informed investment decisions. Conversely, if layoffs result from a temporary market downturn or external factors, investors should evaluate the long-term prospects before proceeding.\n\nIf a company provides a 60-day notice under the WARN Act, then this period should be used strategically to gather intelligence and assess the potential impact on the market. Investors who act swiftly during this window can gain a competitive advantage by positioning themselves as preferred buyers or partners.\n\nIf state-specific WARN Act regulations impose additional requirements, then companies must tailor their compliance strategies to align with local laws. This may involve coordinating with legal advisors and local agencies to ensure full compliance and mitigate potential risks associated with non-compliance.\n\n## Opportunity Playbook\nTo capitalize on opportunities arising from WARN Act notices, asset buyers should adopt a proactive approach to market research and relationship building. Establishing connections with industry insiders, legal experts, and financial advisors can provide valuable insights into potential acquisition targets.\n\nFor example, when retail giant Macy's announced layoffs and store closures in 2025, savvy investors seized the opportunity to acquire prime retail locations at discounted prices. By leveraging their understanding of the real estate market and consumer trends, these investors were able to repurpose the properties for alternative uses, such as mixed-use developments and e-commerce fulfillment centers. ![Abstract warm gradient with light flares](https://images.unsplash.com/photo-1761682247650-29240975b890?crop=entropy&cs=tinysrgb&fit=max&fm=jpg&ixid=M3w4ODA0MDZ8MHwxfHNlYXJjaHwzfHx0aGUlMjBkYXklMjBub3RpY2UlMjBkZWVwfGVufDF8MHx8fDE3NzE3ODAxMzh8MA&ixlib=rb-4.1.0&q=80&w=1080&w=1200&q=80)\n*Photo: Photo by [Liana S](https://unsplash.com/@cherstve_pechivo) on [Unsplash](https://unsplash.com)*\n\nSimilarly, when energy company Chevron announced layoffs due to declining oil prices and shifting energy demands, distressed asset buyers identified opportunities to acquire valuable assets, such as drilling equipment and infrastructure, at a fraction of their original cost. By anticipating future market conditions and aligning their investment strategies with industry trends, these buyers were able to achieve significant returns on their investments.\n\n## Common Mistakes\n- **Ignoring Market Trends:** Failing to stay informed about industry developments can lead to missed opportunities and poor investment decisions.\n- **Inadequate Due Diligence:** Skipping thorough financial analysis can result in overpaying for assets or acquiring liabilities.\n- **Non-Compliance with Legal Requirements:** Overlooking WARN Act regulations can result in costly penalties and legal challenges.\n- **Overestimating Asset Value:** Misjudging the market value of a company's assets can lead to financial losses.\n- **Underestimating Integration Costs:** Failing to account for the costs of integrating acquired assets into existing operations can impact profitability.\n- **Rushing the Acquisition Process:** Hasty decision-making can result in unfavorable terms and missed red flags.\n- **Neglecting Employee Considerations:** Overlooking the impact of layoffs on remaining employees can affect morale and productivity.\n- **Lack of Strategic Planning:** Approaching acquisitions without a clear strategy can lead to misaligned objectives and outcomes.\n- **Ignoring State-Specific Regulations:** Failing to consider local WARN Act requirements can complicate compliance efforts.\n- **Underestimating Competitive Pressures:** Overlooking the actions of competitors can result in missed opportunities and market share loss.\n\n## How DispoSight Helps\nDispoSight's platform offers a powerful tool for professionals seeking to identify and capitalize on corporate distress signals. By providing real-time alerts and comprehensive analysis, DispoSight enables users to stay informed about potential acquisition targets and market trends. Our platform's advanced analytics and data-driven insights empower investors to make informed decisions and optimize their strategies for asset recovery and distressed investing.\n\n## Frequently Asked Questions\n- **What is the WARN Act's 60-day notice requirement?** The WARN Act mandates that employers with 100 or more employees provide a 60-day written notice of mass layoffs or plant closures to affected workers, state dislocated worker units, and local governments.\n- **What are the penalties for non-compliance with the WARN Act?** Employers may face penalties including back pay for each day of violation and a $500 fine for each day of non-compliance.\n- **Are there exceptions to the WARN Act's 60-day notice rule?** Yes, exceptions include unforeseeable business circumstances, natural disasters, and faltering company exceptions.\n- **How can distressed asset buyers benefit from WARN Act notices?** The 60-day notice period provides an opportunity to assess potential acquisition targets and prepare for opportunities arising from the company's financial challenges.\n- **Do all states have the same WARN Act regulations?** No, many states have implemented their own versions of the WARN Act with varying thresholds and requirements.\n- **How can I stay informed about potential acquisition targets?** Monitor news outlets, industry reports, and financial disclosures for signs of corporate distress and leverage platforms like DispoSight for real-time alerts and analysis.\n- **What role does due diligence play in the acquisition process?** Due diligence is crucial for assessing a company's financial health, asset value, and compliance with legal requirements to make informed investment decisions.\n- **What strategies can help mitigate risks in distressed asset acquisitions?** Conduct thorough market research, engage with industry experts, and develop a clear strategic plan to navigate potential challenges and capitalize on opportunities.\n\n## Action Plan\n1. Monitor industry news and financial reports for signs of corporate distress.\n2. Conduct comprehensive due diligence on potential acquisition targets.\n3. Evaluate the market value of a company's assets with expert appraisals.\n4. Ensure compliance with the WARN Act and state-specific regulations.\n5. Engage with legal counsel to navigate complex regulatory requirements.\n6. Develop a strategic acquisition plan aligned with market trends.\n7. Build relationships with industry insiders for valuable insights.\n8. Prepare for integration costs and potential operational challenges.\n9. Act swiftly during the 60-day notice period to gain competitive advantage.\n10. Leverage DispoSight's platform for real-time alerts and data-driven analysis.\n\n## Related Reading\n- [How WARN Act Filings Create Early-Warning Signals for Asset Buyers](/blog/how-warn-act-filings-create-early-warning-signals-for-asset-buyers)\n- [Distressed Asset Investment Opportunities: A Strategic Analysis](/blog/distressed-asset-investment-opportunities-a-strategic-analysis)\n- [Understanding Orderly Liquidation Value in Liquidation Strategy](/blog/understanding-orderly-liquidation-value-in-liquidation-strategy)\n- [Navigating Distressed Asset Sales in Equipment Remarketing](/blog/navigating-distressed-asset-sales-in-equipment-remarketing)\n\n## Disclaimer\nThis article is intended for informational purposes only and should not be construed as legal or financial advice. Readers are encouraged to conduct their own due diligence and consult with legal and financial professionals before making any investment decisions. Compliance with the WARN Act and other regulatory requirements is essential to mitigating risks and ensuring successful outcomes in distressed asset acquisitions.",
  "category": "warn-act",
  "tags": [
    "WARN Act",
    "layoffs",
    "corporate distress",
    "employment law",
    "asset recovery",
    "business liquidation",
    "distressed investing"
  ],
  "primaryKeyword": "layoff 60 day notice",
  "author": {
    "name": "DispoSight Research",
    "role": "Market Intelligence Team",
    "bio": "The DispoSight Research team monitors corporate distress signals across WARN Act filings, bankruptcy courts, SEC filings, and global news to surface asset disposition opportunities for deal-driven organizations."
  },
  "heroImage": {
    "url": "https://images.unsplash.com/photo-1752151140057-9940395553d4?crop=entropy&cs=tinysrgb&fit=max&fm=jpg&ixid=M3w4ODA0MDZ8MHwxfHNlYXJjaHwxfHx0aGUlMjBkYXklMjBub3RpY2UlMjBkZWVwfGVufDF8MHx8fDE3NzE3ODAxMzh8MA&ixlib=rb-4.1.0&q=80&w=1080&w=1200&q=80",
    "alt": "Sand and sediment in turquoise water.",
    "credit": "Photo by [R_ INVSCIMENTO](https://unsplash.com/@r_inascimento) on [Unsplash](https://unsplash.com)"
  },
  "images": [
    {
      "url": "https://images.unsplash.com/photo-1588253197754-420d2d818035?crop=entropy&cs=tinysrgb&fit=max&fm=jpg&ixid=M3w4ODA0MDZ8MHwxfHNlYXJjaHwxfHxsYXlvZmZzJTIwY29ycG9yYXRlfGVufDF8MHx8fDE3NzE3ODAxMzl8MA&ixlib=rb-4.1.0&q=80&w=1080&w=1200&q=80",
      "alt": "black and white building during daytime",
      "credit": "Photo by [Abhishek Anand](https://unsplash.com/@anand__a) on [Unsplash](https://unsplash.com)"
    },
    {
      "url": "https://images.unsplash.com/photo-1633690803733-dbd3e4cbb405?crop=entropy&cs=tinysrgb&fit=max&fm=jpg&ixid=M3w4ODA0MDZ8MHwxfHNlYXJjaHwyfHx0aGUlMjBkYXklMjBub3RpY2UlMjBkZWVwfGVufDF8MHx8fDE3NzE3ODAxMzh8MA&ixlib=rb-4.1.0&q=80&w=1080&w=1200&q=80",
      "alt": "a kite is flying high in the sky",
      "credit": "Photo by [Marcos Romero](https://unsplash.com/@marcos265) on [Unsplash](https://unsplash.com)"
    },
    {
      "url": "https://images.unsplash.com/photo-1761682247650-29240975b890?crop=entropy&cs=tinysrgb&fit=max&fm=jpg&ixid=M3w4ODA0MDZ8MHwxfHNlYXJjaHwzfHx0aGUlMjBkYXklMjBub3RpY2UlMjBkZWVwfGVufDF8MHx8fDE3NzE3ODAxMzh8MA&ixlib=rb-4.1.0&q=80&w=1080&w=1200&q=80",
      "alt": "Abstract warm gradient with light flares",
      "credit": "Photo by [Liana S](https://unsplash.com/@cherstve_pechivo) on [Unsplash](https://unsplash.com)"
    }
  ],
  "headings": [
    {
      "level": 2,
      "text": "Quick Answer",
      "id": "quick-answer"
    },
    {
      "level": 2,
      "text": "Market Snapshot",
      "id": "market-snapshot"
    },
    {
      "level": 2,
      "text": "Step-by-Step Guide",
      "id": "step-by-step-guide"
    },
    {
      "level": 2,
      "text": "Decision Framework",
      "id": "decision-framework"
    },
    {
      "level": 2,
      "text": "Opportunity Playbook",
      "id": "opportunity-playbook"
    },
    {
      "level": 2,
      "text": "Common Mistakes",
      "id": "common-mistakes"
    },
    {
      "level": 2,
      "text": "How DispoSight Helps",
      "id": "how-disposight-helps"
    },
    {
      "level": 2,
      "text": "Frequently Asked Questions",
      "id": "frequently-asked-questions"
    },
    {
      "level": 2,
      "text": "Action Plan",
      "id": "action-plan"
    },
    {
      "level": 2,
      "text": "Related Reading",
      "id": "related-reading"
    },
    {
      "level": 2,
      "text": "Disclaimer",
      "id": "disclaimer"
    }
  ],
  "faqs": [
    {
      "question": "What is the WARN Act's 60-day notice requirement?",
      "answer": "The WARN Act mandates that employers with 100 or more employees provide a 60-day written notice of mass layoffs or plant closures to affected workers, state dislocated worker units, and local governments."
    },
    {
      "question": "What are the penalties for non-compliance with the WARN Act?",
      "answer": "Employers may face penalties including back pay for each day of violation and a $500 fine for each day of non-compliance."
    },
    {
      "question": "Are there exceptions to the WARN Act's 60-day notice rule?",
      "answer": "Yes, exceptions include unforeseeable business circumstances, natural disasters, and faltering company exceptions."
    },
    {
      "question": "How can distressed asset buyers benefit from WARN Act notices?",
      "answer": "The 60-day notice period provides an opportunity to assess potential acquisition targets and prepare for opportunities arising from the company's financial challenges."
    },
    {
      "question": "Do all states have the same WARN Act regulations?",
      "answer": "No, many states have implemented their own versions of the WARN Act with varying thresholds and requirements."
    },
    {
      "question": "How can I stay informed about potential acquisition targets?",
      "answer": "Monitor news outlets, industry reports, and financial disclosures for signs of corporate distress and leverage platforms like DispoSight for real-time alerts and analysis."
    },
    {
      "question": "What role does due diligence play in the acquisition process?",
      "answer": "Due diligence is crucial for assessing a company's financial health, asset value, and compliance with legal requirements to make informed investment decisions."
    },
    {
      "question": "What strategies can help mitigate risks in distressed asset acquisitions?",
      "answer": "Conduct thorough market research, engage with industry experts, and develop a clear strategic plan to navigate potential challenges and capitalize on opportunities."
    },
    {
      "question": "Does the WARN Act apply if a company files for bankruptcy?",
      "answer": "Yes, the WARN Act remains applicable in certain bankruptcy situations. If an employer knew about a plant closing or mass layoff before filing for bankruptcy and failed to provide notice, or if the employer continues to operate the business as a 'debtor in possession' during bankruptcy, WARN obligations still apply. However, if a bankruptcy trustee is solely liquidating the business, WARN requirements generally do not apply."
    },
    {
      "question": "How does the WARN Act define a 'mass layoff'?",
      "answer": "A 'mass layoff' under the WARN Act is defined as a reduction in force that is not a result of a plant closing and results in an employment loss at a single site of employment during any 30-day period for: (1) at least 33% of the full-time employees, provided that at least 50 employees are affected; or (2) at least 500 full-time employees, regardless of the percentage of the workforce."
    },
    {
      "question": "Who is responsible for providing WARN Act notice in the sale of a business?",
      "answer": "In the event of a business sale, the seller is responsible for providing WARN Act notice for any plant closing or mass layoff occurring up to and including the effective date of the sale. After the sale, the buyer assumes responsibility for providing notice for any subsequent plant closings or mass layoffs."
    }
  ],
  "sources": [
    {
      "title": "U.S. Department of Labor - WARN Act Compliance Assistance",
      "url": "https://www.dol.gov/agencies/eta/layoffs/warn"
    },
    {
      "title": "Bureau of Labor Statistics - Mass Layoffs",
      "url": "https://www.bls.gov/mls/"
    },
    {
      "title": "General Electric Restructuring Announcement",
      "url": "https://www.ge.com/news/press-releases/ge-restructuring-layoffs-2025"
    },
    {
      "title": "Ford Motor Company's Plant Closures",
      "url": "https://www.ford.com/newsroom/layoffs-plant-closures-2025"
    },
    {
      "title": "Macy's Store Closures and Layoffs",
      "url": "https://www.macysinc.com/newsroom/press-releases/2025/layoffs-and-closures"
    }
  ],
  "cta": {
    "headline": "Automate Your WARN Act Monitoring",
    "description": "DispoSight pulls WARN filings from every state, scores them for asset potential, and delivers the highest-value opportunities straight to your dashboard. No more manual searching.",
    "buttonText": "Start Your Free Trial",
    "buttonUrl": "/register"
  },
  "wordCount": 1764,
  "readingTime": 8,
  "publishedAt": "2026-02-22T17:08:57.345Z",
  "updatedAt": "2026-02-22T17:08:57.345Z",
  "isDraft": false
}